zscaler_python_sdk/__init__.py
zscaler_python_sdk/lib/README.md
zscaler_python_sdk/lib/__init__.py
zscaler_python_sdk/lib/admin.py
zscaler_python_sdk/lib/api.py
zscaler_python_sdk/lib/auth.py
zscaler_python_sdk/lib/firewall_rules.py
zscaler_python_sdk/lib/url_categories.py
zscaler_python_sdk/lib/url_filtering_rules.py
zscaler_python_sdk/lib/users.py
zscaler_python_sdk/utils.py
zscaler_python_sdk/zia.py
zscaler_python_sdk-0.2.1.dist-info/WHEEL
zscaler_python_sdk-0.2.1.dist-info/METADATA
zscaler_python_sdk-0.2.1.dist-info/RECORD
