Metadata-Version: 2.1
Name: zscaler-python-sdk
Version: 0.2.1
Summary: Unofficial Zscaler API python sdk
Home-page: https://github.com/yuta519/zscaler-python-sdk
License: MIT
Author: yuta519
Author-email: yuta519.ka23tf@docomo.ne.jp
Requires-Python: >=3.9,<4.0
Classifier: License :: OSI Approved :: MIT License
Classifier: Programming Language :: Python :: 3
Classifier: Programming Language :: Python :: 3.9
Requires-Dist: black (>=21.9b0,<22.0)
Requires-Dist: requests (>=2.26.0,<3.0.0)
